AUTHORS.rst
CONTRIBUTING.rst
HISTORY.rst
LICENSE
MANIFEST.in
README.rst
setup.cfg
setup.py
boxes/__init__.py
boxes/boxes.py
boxes.egg-info/PKG-INFO
boxes.egg-info/SOURCES.txt
boxes.egg-info/dependency_links.txt
boxes.egg-info/not-zip-safe
boxes.egg-info/top_level.txt
docs/Makefile
docs/authors.rst
docs/conf.py
docs/contributing.rst
docs/history.rst
docs/index.rst
docs/installation.rst
docs/make.bat
docs/readme.rst
docs/usage.rst
tests/__init__.py
tests/test_boxes.py