Metadata-Version: 1.1
Name: boxes
Version: 0.0.0
Summary: Example for the book "Boxes".
Home-page: https://github.com/ralsina/boxes
Author: Roberto Alsina
Author-email: roberto.alsina@gmail.com
License: MIT license
Keywords: boxes
Platform: UNKNOWN
Classifier: Development Status :: 2 - Pre-Alpha
Classifier: Intended Audience :: Developers
Classifier: License :: OSI Approved :: MIT License
Classifier: Natural Language :: English
Classifier: Programming Language :: Python :: 2
Classifier: Programming Language :: Python :: 2.7
Classifier: Programming Language :: Python :: 3
Classifier: Programming Language :: Python :: 3.4
Classifier: Programming Language :: Python :: 3.5
Classifier: Programming Language :: Python :: 3.6
